{
	"children":[
		{
			"children":[
				{
					"children":[
						{
							"children":[
								{
									"children":[
										{
											"name":"abgoodslist",
											"path":"D:\\workspace\\dbxmlTool\\src\\main\\resources\\CONF\\D\\AionReal58\\AionMap\\XML\\abgoodslist.json"
										},
										{
											"name":"absolute_stat_to_pc",
											"path":"D:\\workspace\\dbxmlTool\\src\\main\\resources\\CONF\\D\\AionReal58\\AionMap\\XML\\absolute_stat_to_pc.json"
										},
										{
											"name":"abyss",
											"path":"D:\\workspace\\dbxmlTool\\src\\main\\resources\\CONF\\D\\AionReal58\\AionMap\\XML\\abyss.json"
										},
										{
											"name":"abysspoint_world_mod",
											"path":"D:\\workspace\\dbxmlTool\\src\\main\\resources\\CONF\\D\\AionReal58\\AionMap\\XML\\abysspoint_world_mod.json"
										},
										{
											"name":"abyss_leader_skill",
											"path":"D:\\workspace\\dbxmlTool\\src\\main\\resources\\CONF\\D\\AionReal58\\AionMap\\XML\\abyss_leader_skill.json"
										},
										{
											"name":"abyss_mist_times",
											"path":"D:\\workspace\\dbxmlTool\\src\\main\\resources\\CONF\\D\\AionReal58\\AionMap\\XML\\abyss_mist_times.json"
										},
										{
											"name":"abyss_op",
											"path":"D:\\workspace\\dbxmlTool\\src\\main\\resources\\CONF\\D\\AionReal58\\AionMap\\XML\\abyss_op.json"
										},
										{
											"name":"abyss_race_bonuses",
											"path":"D:\\workspace\\dbxmlTool\\src\\main\\resources\\CONF\\D\\AionReal58\\AionMap\\XML\\abyss_race_bonuses.json"
										},
										{
											"name":"airline",
											"path":"D:\\workspace\\dbxmlTool\\src\\main\\resources\\CONF\\D\\AionReal58\\AionMap\\XML\\airline.json"
										},
										{
											"name":"airports",
											"path":"D:\\workspace\\dbxmlTool\\src\\main\\resources\\CONF\\D\\AionReal58\\AionMap\\XML\\airports.json"
										},
										{
											"children":[
												{
													"name":"'Tesinon_Dimension",
													"path":"D:\\workspace\\dbxmlTool\\src\\main\\resources\\CONF\\D\\AionReal58\\AionMap\\XML\\AnimationMarkers\\'Tesinon_Dimension.json"
												}
											],
											"name":"AnimationMarkers",
											"path":"D:\\workspace\\dbxmlTool\\src\\main\\resources\\CONF\\D\\AionReal58\\AionMap\\XML\\AnimationMarkers"
										},
										{
											"name":"boost_time_table",
											"path":"D:\\workspace\\dbxmlTool\\src\\main\\resources\\CONF\\D\\AionReal58\\AionMap\\XML\\boost_time_table.json"
										},
										{
											"name":"boost_time_table_level_step",
											"path":"D:\\workspace\\dbxmlTool\\src\\main\\resources\\CONF\\D\\AionReal58\\AionMap\\XML\\boost_time_table_level_step.json"
										},
										{
											"name":"boost_time_table_level_step_inter",
											"path":"D:\\workspace\\dbxmlTool\\src\\main\\resources\\CONF\\D\\AionReal58\\AionMap\\XML\\boost_time_table_level_step_inter.json"
										},
										{
											"name":"boost_time_table_level_step_test",
											"path":"D:\\workspace\\dbxmlTool\\src\\main\\resources\\CONF\\D\\AionReal58\\AionMap\\XML\\boost_time_table_level_step_test.json"
										},
										{
											"name":"boost_time_table_level_step_test_inter",
											"path":"D:\\workspace\\dbxmlTool\\src\\main\\resources\\CONF\\D\\AionReal58\\AionMap\\XML\\boost_time_table_level_step_test_inter.json"
										},
										{
											"name":"boost_time_table_no_level_step",
											"path":"D:\\workspace\\dbxmlTool\\src\\main\\resources\\CONF\\D\\AionReal58\\AionMap\\XML\\boost_time_table_no_level_step.json"
										},
										{
											"name":"boost_time_table_no_level_step_inter",
											"path":"D:\\workspace\\dbxmlTool\\src\\main\\resources\\CONF\\D\\AionReal58\\AionMap\\XML\\boost_time_table_no_level_step_inter.json"
										},
										{
											"name":"boost_time_table_no_level_step_test",
											"path":"D:\\workspace\\dbxmlTool\\src\\main\\resources\\CONF\\D\\AionReal58\\AionMap\\XML\\boost_time_table_no_level_step_test.json"
										},
										{
											"name":"boost_time_table_no_level_step_test_inter",
											"path":"D:\\workspace\\dbxmlTool\\src\\main\\resources\\CONF\\D\\AionReal58\\AionMap\\XML\\boost_time_table_no_level_step_test_inter.json"
										},
										{
											"name":"challenge_task",
											"path":"D:\\workspace\\dbxmlTool\\src\\main\\resources\\CONF\\D\\AionReal58\\AionMap\\XML\\challenge_task.json"
										},
										{
											"children":[
												{
													"name":"abyss_mist_times",
													"path":"D:\\workspace\\dbxmlTool\\src\\main\\resources\\CONF\\D\\AionReal58\\AionMap\\XML\\China\\abyss_mist_times.json"
												},
												{
													"name":"bm_config",
													"path":"D:\\workspace\\dbxmlTool\\src\\main\\resources\\CONF\\D\\AionReal58\\AionMap\\XML\\China\\bm_config.json"
												},
												{
													"name":"boost_time_table_level_step",
													"path":"D:\\workspace\\dbxmlTool\\src\\main\\resources\\CONF\\D\\AionReal58\\AionMap\\XML\\China\\boost_time_table_level_step.json"
												},
												{
													"name":"boost_time_table_level_step_inter",
													"path":"D:\\workspace\\dbxmlTool\\src\\main\\resources\\CONF\\D\\AionReal58\\AionMap\\XML\\China\\boost_time_table_level_step_inter.json"
												},
												{
													"name":"boost_time_table_no_level_step",
													"path":"D:\\workspace\\dbxmlTool\\src\\main\\resources\\CONF\\D\\AionReal58\\AionMap\\XML\\China\\boost_time_table_no_level_step.json"
												},
												{
													"name":"boost_time_table_no_level_step_inter",
													"path":"D:\\workspace\\dbxmlTool\\src\\main\\resources\\CONF\\D\\AionReal58\\AionMap\\XML\\China\\boost_time_table_no_level_step_inter.json"
												},
												{
													"name":"CommonDropItems",
													"path":"D:\\workspace\\dbxmlTool\\src\\main\\resources\\CONF\\D\\AionReal58\\AionMap\\XML\\China\\CommonDropItems.json"
												},
												{
													"name":"familiar_contract",
													"path":"D:\\workspace\\dbxmlTool\\src\\main\\resources\\CONF\\D\\AionReal58\\AionMap\\XML\\China\\familiar_contract.json"
												},
												{
													"name":"familiar_sgrade_ratio",
													"path":"D:\\workspace\\dbxmlTool\\src\\main\\resources\\CONF\\D\\AionReal58\\AionMap\\XML\\China\\familiar_sgrade_ratio.json"
												},
												{
													"name":"game_config",
													"path":"D:\\workspace\\dbxmlTool\\src\\main\\resources\\CONF\\D\\AionReal58\\AionMap\\XML\\China\\game_config.json"
												},
												{
													"name":"goodslist",
													"path":"D:\\workspace\\dbxmlTool\\src\\main\\resources\\CONF\\D\\AionReal58\\AionMap\\XML\\China\\goodslist.json"
												},
												{
													"name":"gotchas",
													"path":"D:\\workspace\\dbxmlTool\\src\\main\\resources\\CONF\\D\\AionReal58\\AionMap\\XML\\China\\gotchas.json"
												},
												{
													"name":"gotcha_rewards",
													"path":"D:\\workspace\\dbxmlTool\\src\\main\\resources\\CONF\\D\\AionReal58\\AionMap\\XML\\China\\gotcha_rewards.json"
												},
												{
													"name":"instance_cooltime",
													"path":"D:\\workspace\\dbxmlTool\\src\\main\\resources\\CONF\\D\\AionReal58\\AionMap\\XML\\China\\instance_cooltime.json"
												},
												{
													"name":"instance_cooltime2",
													"path":"D:\\workspace\\dbxmlTool\\src\\main\\resources\\CONF\\D\\AionReal58\\AionMap\\XML\\China\\instance_cooltime2.json"
												},
												{
													"name":"instant_dungeon_battleground",
													"path":"D:\\workspace\\dbxmlTool\\src\\main\\resources\\CONF\\D\\AionReal58\\AionMap\\XML\\China\\instant_dungeon_battleground.json"
												},
												{
													"name":"instant_dungeon_tournament",
													"path":"D:\\workspace\\dbxmlTool\\src\\main\\resources\\CONF\\D\\AionReal58\\AionMap\\XML\\China\\instant_dungeon_tournament.json"
												},
												{
													"name":"items",
													"path":"D:\\workspace\\dbxmlTool\\src\\main\\resources\\CONF\\D\\AionReal58\\AionMap\\XML\\China\\items.json"
												},
												{
													"name":"item_accessories",
													"path":"D:\\workspace\\dbxmlTool\\src\\main\\resources\\CONF\\D\\AionReal58\\AionMap\\XML\\China\\item_accessories.json"
												},
												{
													"name":"item_armors",
													"path":"D:\\workspace\\dbxmlTool\\src\\main\\resources\\CONF\\D\\AionReal58\\AionMap\\XML\\China\\item_armors.json"
												},
												{
													"name":"item_etc",
													"path":"D:\\workspace\\dbxmlTool\\src\\main\\resources\\CONF\\D\\AionReal58\\AionMap\\XML\\China\\item_etc.json"
												},
												{
													"name":"item_quest",
													"path":"D:\\workspace\\dbxmlTool\\src\\main\\resources\\CONF\\D\\AionReal58\\AionMap\\XML\\China\\item_quest.json"
												},
												{
													"name":"item_weapons",
													"path":"D:\\workspace\\dbxmlTool\\src\\main\\resources\\CONF\\D\\AionReal58\\AionMap\\XML\\China\\item_weapons.json"
												},
												{
													"name":"login_event",
													"path":"D:\\workspace\\dbxmlTool\\src\\main\\resources\\CONF\\D\\AionReal58\\AionMap\\XML\\China\\login_event.json"
												},
												{
													"name":"pcexp_table",
													"path":"D:\\workspace\\dbxmlTool\\src\\main\\resources\\CONF\\D\\AionReal58\\AionMap\\XML\\China\\pcexp_table.json"
												},
												{
													"name":"quest",
													"path":"D:\\workspace\\dbxmlTool\\src\\main\\resources\\CONF\\D\\AionReal58\\AionMap\\XML\\China\\quest.json"
												},
												{
													"name":"quest_random_rewards",
													"path":"D:\\workspace\\dbxmlTool\\src\\main\\resources\\CONF\\D\\AionReal58\\AionMap\\XML\\China\\quest_random_rewards.json"
												},
												{
													"name":"ranking",
													"path":"D:\\workspace\\dbxmlTool\\src\\main\\resources\\CONF\\D\\AionReal58\\AionMap\\XML\\China\\ranking.json"
												},
												{
													"name":"special_server_config",
													"path":"D:\\workspace\\dbxmlTool\\src\\main\\resources\\CONF\\D\\AionReal58\\AionMap\\XML\\China\\special_server_config.json"
												},
												{
													"name":"trade_in_list",
													"path":"D:\\workspace\\dbxmlTool\\src\\main\\resources\\CONF\\D\\AionReal58\\AionMap\\XML\\China\\trade_in_list.json"
												}
											],
											"name":"China",
											"path":"D:\\workspace\\dbxmlTool\\src\\main\\resources\\CONF\\D\\AionReal58\\AionMap\\XML\\China"
										},
										{
											"name":"client_strings_bm",
											"path":"D:\\workspace\\dbxmlTool\\src\\main\\resources\\CONF\\D\\AionReal58\\AionMap\\XML\\client_strings_bm.json"
										},
										{
											"name":"client_strings_bmrestrict",
											"path":"D:\\workspace\\dbxmlTool\\src\\main\\resources\\CONF\\D\\AionReal58\\AionMap\\XML\\client_strings_bmrestrict.json"
										},
										{
											"name":"client_strings_dic_etc",
											"path":"D:\\workspace\\dbxmlTool\\src\\main\\resources\\CONF\\D\\AionReal58\\AionMap\\XML\\client_strings_dic_etc.json"
										},
										{
											"name":"client_strings_dic_item",
											"path":"D:\\workspace\\dbxmlTool\\src\\main\\resources\\CONF\\D\\AionReal58\\AionMap\\XML\\client_strings_dic_item.json"
										},
										{
											"name":"client_strings_dic_people",
											"path":"D:\\workspace\\dbxmlTool\\src\\main\\resources\\CONF\\D\\AionReal58\\AionMap\\XML\\client_strings_dic_people.json"
										},
										{
											"name":"client_strings_dic_place",
											"path":"D:\\workspace\\dbxmlTool\\src\\main\\resources\\CONF\\D\\AionReal58\\AionMap\\XML\\client_strings_dic_place.json"
										},
										{
											"name":"client_strings_etc",
											"path":"D:\\workspace\\dbxmlTool\\src\\main\\resources\\CONF\\D\\AionReal58\\AionMap\\XML\\client_strings_etc.json"
										},
										{
											"name":"client_strings_funcpet",
											"path":"D:\\workspace\\dbxmlTool\\src\\main\\resources\\CONF\\D\\AionReal58\\AionMap\\XML\\client_strings_funcpet.json"
										},
										{
											"name":"client_strings_gossip",
											"path":"D:\\workspace\\dbxmlTool\\src\\main\\resources\\CONF\\D\\AionReal58\\AionMap\\XML\\client_strings_gossip.json"
										},
										{
											"name":"client_strings_item",
											"path":"D:\\workspace\\dbxmlTool\\src\\main\\resources\\CONF\\D\\AionReal58\\AionMap\\XML\\client_strings_item.json"
										},
										{
											"name":"client_strings_item2",
											"path":"D:\\workspace\\dbxmlTool\\src\\main\\resources\\CONF\\D\\AionReal58\\AionMap\\XML\\client_strings_item2.json"
										},
										{
											"name":"client_strings_item3",
											"path":"D:\\workspace\\dbxmlTool\\src\\main\\resources\\CONF\\D\\AionReal58\\AionMap\\XML\\client_strings_item3.json"
										},
										{
											"name":"client_strings_level",
											"path":"D:\\workspace\\dbxmlTool\\src\\main\\resources\\CONF\\D\\AionReal58\\AionMap\\XML\\client_strings_level.json"
										},
										{
											"name":"client_strings_msg",
											"path":"D:\\workspace\\dbxmlTool\\src\\main\\resources\\CONF\\D\\AionReal58\\AionMap\\XML\\client_strings_msg.json"
										},
										{
											"name":"client_strings_override",
											"path":"D:\\workspace\\dbxmlTool\\src\\main\\resources\\CONF\\D\\AionReal58\\AionMap\\XML\\client_strings_override.json"
										},
										{
											"name":"client_strings_quest",
											"path":"D:\\workspace\\dbxmlTool\\src\\main\\resources\\CONF\\D\\AionReal58\\AionMap\\XML\\client_strings_quest.json"
										},
										{
											"name":"client_strings_skill",
											"path":"D:\\workspace\\dbxmlTool\\src\\main\\resources\\CONF\\D\\AionReal58\\AionMap\\XML\\client_strings_skill.json"
										},
										{
											"name":"client_strings_ui",
											"path":"D:\\workspace\\dbxmlTool\\src\\main\\resources\\CONF\\D\\AionReal58\\AionMap\\XML\\client_strings_ui.json"
										},
										{
											"name":"data_driven_quest",
											"path":"D:\\workspace\\dbxmlTool\\src\\main\\resources\\CONF\\D\\AionReal58\\AionMap\\XML\\data_driven_quest.json"
										},
										{
											"name":"devanion_skill_enchant",
											"path":"D:\\workspace\\dbxmlTool\\src\\main\\resources\\CONF\\D\\AionReal58\\AionMap\\XML\\devanion_skill_enchant.json"
										},
										{
											"name":"exceed_skillset",
											"path":"D:\\workspace\\dbxmlTool\\src\\main\\resources\\CONF\\D\\AionReal58\\AionMap\\XML\\exceed_skillset.json"
										},
										{
											"name":"familiars",
											"path":"D:\\workspace\\dbxmlTool\\src\\main\\resources\\CONF\\D\\AionReal58\\AionMap\\XML\\familiars.json"
										},
										{
											"name":"familiar_contract",
											"path":"D:\\workspace\\dbxmlTool\\src\\main\\resources\\CONF\\D\\AionReal58\\AionMap\\XML\\familiar_contract.json"
										},
										{
											"name":"familiar_sgrade_ratio",
											"path":"D:\\workspace\\dbxmlTool\\src\\main\\resources\\CONF\\D\\AionReal58\\AionMap\\XML\\familiar_sgrade_ratio.json"
										},
										{
											"name":"gameexperience_setting_items",
											"path":"D:\\workspace\\dbxmlTool\\src\\main\\resources\\CONF\\D\\AionReal58\\AionMap\\XML\\gameexperience_setting_items.json"
										},
										{
											"name":"goodslist",
											"path":"D:\\workspace\\dbxmlTool\\src\\main\\resources\\CONF\\D\\AionReal58\\AionMap\\XML\\goodslist.json"
										},
										{
											"name":"gotchas",
											"path":"D:\\workspace\\dbxmlTool\\src\\main\\resources\\CONF\\D\\AionReal58\\AionMap\\XML\\gotchas.json"
										},
										{
											"name":"gotcha_rewards",
											"path":"D:\\workspace\\dbxmlTool\\src\\main\\resources\\CONF\\D\\AionReal58\\AionMap\\XML\\gotcha_rewards.json"
										},
										{
											"name":"guild_rank_reward",
											"path":"D:\\workspace\\dbxmlTool\\src\\main\\resources\\CONF\\D\\AionReal58\\AionMap\\XML\\guild_rank_reward.json"
										},
										{
											"name":"housing_address",
											"path":"D:\\workspace\\dbxmlTool\\src\\main\\resources\\CONF\\D\\AionReal58\\AionMap\\XML\\housing_address.json"
										},
										{
											"name":"housing_building",
											"path":"D:\\workspace\\dbxmlTool\\src\\main\\resources\\CONF\\D\\AionReal58\\AionMap\\XML\\housing_building.json"
										},
										{
											"name":"housing_custom_part",
											"path":"D:\\workspace\\dbxmlTool\\src\\main\\resources\\CONF\\D\\AionReal58\\AionMap\\XML\\housing_custom_part.json"
										},
										{
											"name":"housing_land",
											"path":"D:\\workspace\\dbxmlTool\\src\\main\\resources\\CONF\\D\\AionReal58\\AionMap\\XML\\housing_land.json"
										},
										{
											"name":"housing_object",
											"path":"D:\\workspace\\dbxmlTool\\src\\main\\resources\\CONF\\D\\AionReal58\\AionMap\\XML\\housing_object.json"
										},
										{
											"name":"housing_object_place_tag",
											"path":"D:\\workspace\\dbxmlTool\\src\\main\\resources\\CONF\\D\\AionReal58\\AionMap\\XML\\housing_object_place_tag.json"
										},
										{
											"name":"housing_town",
											"path":"D:\\workspace\\dbxmlTool\\src\\main\\resources\\CONF\\D\\AionReal58\\AionMap\\XML\\housing_town.json"
										},
										{
											"name":"instance_bonusattr",
											"path":"D:\\workspace\\dbxmlTool\\src\\main\\resources\\CONF\\D\\AionReal58\\AionMap\\XML\\instance_bonusattr.json"
										},
										{
											"name":"instance_cooltime",
											"path":"D:\\workspace\\dbxmlTool\\src\\main\\resources\\CONF\\D\\AionReal58\\AionMap\\XML\\instance_cooltime.json"
										},
										{
											"name":"instance_cooltime2",
											"path":"D:\\workspace\\dbxmlTool\\src\\main\\resources\\CONF\\D\\AionReal58\\AionMap\\XML\\instance_cooltime2.json"
										},
										{
											"name":"instance_creation",
											"path":"D:\\workspace\\dbxmlTool\\src\\main\\resources\\CONF\\D\\AionReal58\\AionMap\\XML\\instance_creation.json"
										},
										{
											"name":"instance_pool",
											"path":"D:\\workspace\\dbxmlTool\\src\\main\\resources\\CONF\\D\\AionReal58\\AionMap\\XML\\instance_pool.json"
										},
										{
											"name":"instance_restrict",
											"path":"D:\\workspace\\dbxmlTool\\src\\main\\resources\\CONF\\D\\AionReal58\\AionMap\\XML\\instance_restrict.json"
										},
										{
											"name":"instance_scaling",
											"path":"D:\\workspace\\dbxmlTool\\src\\main\\resources\\CONF\\D\\AionReal58\\AionMap\\XML\\instance_scaling.json"
										},
										{
											"name":"instant_dungeon_battleground",
											"path":"D:\\workspace\\dbxmlTool\\src\\main\\resources\\CONF\\D\\AionReal58\\AionMap\\XML\\instant_dungeon_battleground.json"
										},
										{
											"name":"instant_dungeon_define",
											"path":"D:\\workspace\\dbxmlTool\\src\\main\\resources\\CONF\\D\\AionReal58\\AionMap\\XML\\instant_dungeon_define.json"
										},
										{
											"name":"instant_dungeon_idarenapvp",
											"path":"D:\\workspace\\dbxmlTool\\src\\main\\resources\\CONF\\D\\AionReal58\\AionMap\\XML\\instant_dungeon_idarenapvp.json"
										},
										{
											"name":"instant_dungeon_tournament",
											"path":"D:\\workspace\\dbxmlTool\\src\\main\\resources\\CONF\\D\\AionReal58\\AionMap\\XML\\instant_dungeon_tournament.json"
										},
										{
											"name":"items-gai",
											"path":"D:\\workspace\\dbxmlTool\\src\\main\\resources\\CONF\\D\\AionReal58\\AionMap\\XML\\items-gai.json"
										},
										{
											"name":"items_looting_fx",
											"path":"D:\\workspace\\dbxmlTool\\src\\main\\resources\\CONF\\D\\AionReal58\\AionMap\\XML\\items_looting_fx.json"
										},
										{
											"name":"item_luna",
											"path":"D:\\workspace\\dbxmlTool\\src\\main\\resources\\CONF\\D\\AionReal58\\AionMap\\XML\\item_luna.json"
										},
										{
											"name":"item_multi_return",
											"path":"D:\\workspace\\dbxmlTool\\src\\main\\resources\\CONF\\D\\AionReal58\\AionMap\\XML\\item_multi_return.json"
										},
										{
											"name":"item_option_probability",
											"path":"D:\\workspace\\dbxmlTool\\src\\main\\resources\\CONF\\D\\AionReal58\\AionMap\\XML\\item_option_probability.json"
										},
										{
											"name":"item_prohibit",
											"path":"D:\\workspace\\dbxmlTool\\src\\main\\resources\\CONF\\D\\AionReal58\\AionMap\\XML\\item_prohibit.json"
										},
										{
											"name":"item_random_option",
											"path":"D:\\workspace\\dbxmlTool\\src\\main\\resources\\CONF\\D\\AionReal58\\AionMap\\XML\\item_random_option.json"
										},
										{
											"name":"item_skill_enhance",
											"path":"D:\\workspace\\dbxmlTool\\src\\main\\resources\\CONF\\D\\AionReal58\\AionMap\\XML\\item_skill_enhance.json"
										},
										{
											"name":"item_standard_price",
											"path":"D:\\workspace\\dbxmlTool\\src\\main\\resources\\CONF\\D\\AionReal58\\AionMap\\XML\\item_standard_price.json"
										},
										{
											"name":"jumping_addquest",
											"path":"D:\\workspace\\dbxmlTool\\src\\main\\resources\\CONF\\D\\AionReal58\\AionMap\\XML\\jumping_addquest.json"
										},
										{
											"name":"jumping_endquest",
											"path":"D:\\workspace\\dbxmlTool\\src\\main\\resources\\CONF\\D\\AionReal58\\AionMap\\XML\\jumping_endquest.json"
										},
										{
											"name":"legion_dominion",
											"path":"D:\\workspace\\dbxmlTool\\src\\main\\resources\\CONF\\D\\AionReal58\\AionMap\\XML\\legion_dominion.json"
										},
										{
											"name":"login_event",
											"path":"D:\\workspace\\dbxmlTool\\src\\main\\resources\\CONF\\D\\AionReal58\\AionMap\\XML\\login_event.json"
										},
										{
											"name":"npcfactions_quest",
											"path":"D:\\workspace\\dbxmlTool\\src\\main\\resources\\CONF\\D\\AionReal58\\AionMap\\XML\\npcfactions_quest.json"
										},
										{
											"name":"pcexp_mod_table",
											"path":"D:\\workspace\\dbxmlTool\\src\\main\\resources\\CONF\\D\\AionReal58\\AionMap\\XML\\pcexp_mod_table.json"
										},
										{
											"name":"pcexp_table",
											"path":"D:\\workspace\\dbxmlTool\\src\\main\\resources\\CONF\\D\\AionReal58\\AionMap\\XML\\pcexp_table.json"
										},
										{
											"name":"pc_skill_skin",
											"path":"D:\\workspace\\dbxmlTool\\src\\main\\resources\\CONF\\D\\AionReal58\\AionMap\\XML\\pc_skill_skin.json"
										},
										{
											"name":"polymorph_temp_skill",
											"path":"D:\\workspace\\dbxmlTool\\src\\main\\resources\\CONF\\D\\AionReal58\\AionMap\\XML\\polymorph_temp_skill.json"
										},
										{
											"name":"purchase_list",
											"path":"D:\\workspace\\dbxmlTool\\src\\main\\resources\\CONF\\D\\AionReal58\\AionMap\\XML\\purchase_list.json"
										},
										{
											"name":"pvp_exp_mod_table",
											"path":"D:\\workspace\\dbxmlTool\\src\\main\\resources\\CONF\\D\\AionReal58\\AionMap\\XML\\pvp_exp_mod_table.json"
										},
										{
											"name":"pvp_exp_table",
											"path":"D:\\workspace\\dbxmlTool\\src\\main\\resources\\CONF\\D\\AionReal58\\AionMap\\XML\\pvp_exp_table.json"
										},
										{
											"name":"pvp_mod_table",
											"path":"D:\\workspace\\dbxmlTool\\src\\main\\resources\\CONF\\D\\AionReal58\\AionMap\\XML\\pvp_mod_table.json"
										},
										{
											"name":"pvp_rank",
											"path":"D:\\workspace\\dbxmlTool\\src\\main\\resources\\CONF\\D\\AionReal58\\AionMap\\XML\\pvp_rank.json"
										},
										{
											"name":"pvp_world_adjust",
											"path":"D:\\workspace\\dbxmlTool\\src\\main\\resources\\CONF\\D\\AionReal58\\AionMap\\XML\\pvp_world_adjust.json"
										},
										{
											"name":"Quest_CombineTask",
											"path":"D:\\workspace\\dbxmlTool\\src\\main\\resources\\CONF\\D\\AionReal58\\AionMap\\XML\\Quest_CombineTask.json"
										},
										{
											"name":"Quest_SimpleCollectItem",
											"path":"D:\\workspace\\dbxmlTool\\src\\main\\resources\\CONF\\D\\AionReal58\\AionMap\\XML\\Quest_SimpleCollectItem.json"
										},
										{
											"name":"Quest_SimpleHunt",
											"path":"D:\\workspace\\dbxmlTool\\src\\main\\resources\\CONF\\D\\AionReal58\\AionMap\\XML\\Quest_SimpleHunt.json"
										},
										{
											"name":"Quest_SimpleItemPlay",
											"path":"D:\\workspace\\dbxmlTool\\src\\main\\resources\\CONF\\D\\AionReal58\\AionMap\\XML\\Quest_SimpleItemPlay.json"
										},
										{
											"name":"Quest_SimpleSerialHunt",
											"path":"D:\\workspace\\dbxmlTool\\src\\main\\resources\\CONF\\D\\AionReal58\\AionMap\\XML\\Quest_SimpleSerialHunt.json"
										},
										{
											"name":"Quest_SimpleTalk",
											"path":"D:\\workspace\\dbxmlTool\\src\\main\\resources\\CONF\\D\\AionReal58\\AionMap\\XML\\Quest_SimpleTalk.json"
										},
										{
											"name":"Quest_SimpleUseItem",
											"path":"D:\\workspace\\dbxmlTool\\src\\main\\resources\\CONF\\D\\AionReal58\\AionMap\\XML\\Quest_SimpleUseItem.json"
										},
										{
											"name":"ranking",
											"path":"D:\\workspace\\dbxmlTool\\src\\main\\resources\\CONF\\D\\AionReal58\\AionMap\\XML\\ranking.json"
										},
										{
											"name":"skill_base",
											"path":"D:\\workspace\\dbxmlTool\\src\\main\\resources\\CONF\\D\\AionReal58\\AionMap\\XML\\skill_base.json"
										},
										{
											"name":"skill_charge",
											"path":"D:\\workspace\\dbxmlTool\\src\\main\\resources\\CONF\\D\\AionReal58\\AionMap\\XML\\skill_charge.json"
										},
										{
											"name":"skill_conflictcounts",
											"path":"D:\\workspace\\dbxmlTool\\src\\main\\resources\\CONF\\D\\AionReal58\\AionMap\\XML\\skill_conflictcounts.json"
										},
										{
											"name":"skill_damageattenuation",
											"path":"D:\\workspace\\dbxmlTool\\src\\main\\resources\\CONF\\D\\AionReal58\\AionMap\\XML\\skill_damageattenuation.json"
										},
										{
											"name":"skill_learns",
											"path":"D:\\workspace\\dbxmlTool\\src\\main\\resources\\CONF\\D\\AionReal58\\AionMap\\XML\\skill_learns.json"
										},
										{
											"name":"skill_prohibit",
											"path":"D:\\workspace\\dbxmlTool\\src\\main\\resources\\CONF\\D\\AionReal58\\AionMap\\XML\\skill_prohibit.json"
										},
										{
											"name":"skill_qualification",
											"path":"D:\\workspace\\dbxmlTool\\src\\main\\resources\\CONF\\D\\AionReal58\\AionMap\\XML\\skill_qualification.json"
										},
										{
											"name":"skill_randomdamage",
											"path":"D:\\workspace\\dbxmlTool\\src\\main\\resources\\CONF\\D\\AionReal58\\AionMap\\XML\\skill_randomdamage.json"
										},
										{
											"name":"skill_signetdata",
											"path":"D:\\workspace\\dbxmlTool\\src\\main\\resources\\CONF\\D\\AionReal58\\AionMap\\XML\\skill_signetdata.json"
										},
										{
											"children":[
												{
													"name":"abyss_mist_times_special01",
													"path":"D:\\workspace\\dbxmlTool\\src\\main\\resources\\CONF\\D\\AionReal58\\AionMap\\XML\\Special01\\abyss_mist_times_special01.json"
												},
												{
													"name":"abyss_rank_special01",
													"path":"D:\\workspace\\dbxmlTool\\src\\main\\resources\\CONF\\D\\AionReal58\\AionMap\\XML\\Special01\\abyss_rank_special01.json"
												},
												{
													"name":"abyss_special01",
													"path":"D:\\workspace\\dbxmlTool\\src\\main\\resources\\CONF\\D\\AionReal58\\AionMap\\XML\\Special01\\abyss_special01.json"
												},
												{
													"name":"airline_special01",
													"path":"D:\\workspace\\dbxmlTool\\src\\main\\resources\\CONF\\D\\AionReal58\\AionMap\\XML\\Special01\\airline_special01.json"
												},
												{
													"name":"aitimeconditions_special01",
													"path":"D:\\workspace\\dbxmlTool\\src\\main\\resources\\CONF\\D\\AionReal58\\AionMap\\XML\\Special01\\aitimeconditions_special01.json"
												},
												{
													"name":"board_bm_special01",
													"path":"D:\\workspace\\dbxmlTool\\src\\main\\resources\\CONF\\D\\AionReal58\\AionMap\\XML\\Special01\\board_bm_special01.json"
												},
												{
													"name":"boost_time_table_level_step_inter_special01",
													"path":"D:\\workspace\\dbxmlTool\\src\\main\\resources\\CONF\\D\\AionReal58\\AionMap\\XML\\Special01\\boost_time_table_level_step_inter_special01.json"
												},
												{
													"name":"boost_time_table_level_step_special01",
													"path":"D:\\workspace\\dbxmlTool\\src\\main\\resources\\CONF\\D\\AionReal58\\AionMap\\XML\\Special01\\boost_time_table_level_step_special01.json"
												},
												{
													"name":"boost_time_table_level_step_test_inter_special01",
													"path":"D:\\workspace\\dbxmlTool\\src\\main\\resources\\CONF\\D\\AionReal58\\AionMap\\XML\\Special01\\boost_time_table_level_step_test_inter_special01.json"
												},
												{
													"name":"boost_time_table_level_step_test_special01",
													"path":"D:\\workspace\\dbxmlTool\\src\\main\\resources\\CONF\\D\\AionReal58\\AionMap\\XML\\Special01\\boost_time_table_level_step_test_special01.json"
												},
												{
													"name":"boost_time_table_no_level_step_inter_special01",
													"path":"D:\\workspace\\dbxmlTool\\src\\main\\resources\\CONF\\D\\AionReal58\\AionMap\\XML\\Special01\\boost_time_table_no_level_step_inter_special01.json"
												},
												{
													"name":"boost_time_table_no_level_step_special01",
													"path":"D:\\workspace\\dbxmlTool\\src\\main\\resources\\CONF\\D\\AionReal58\\AionMap\\XML\\Special01\\boost_time_table_no_level_step_special01.json"
												},
												{
													"name":"boost_time_table_no_level_step_test_inter_special01",
													"path":"D:\\workspace\\dbxmlTool\\src\\main\\resources\\CONF\\D\\AionReal58\\AionMap\\XML\\Special01\\boost_time_table_no_level_step_test_inter_special01.json"
												},
												{
													"name":"boost_time_table_no_level_step_test_special01",
													"path":"D:\\workspace\\dbxmlTool\\src\\main\\resources\\CONF\\D\\AionReal58\\AionMap\\XML\\Special01\\boost_time_table_no_level_step_test_special01.json"
												},
												{
													"name":"condspwntimes_special01",
													"path":"D:\\workspace\\dbxmlTool\\src\\main\\resources\\CONF\\D\\AionReal58\\AionMap\\XML\\Special01\\condspwntimes_special01.json"
												},
												{
													"name":"direct_portal_special01",
													"path":"D:\\workspace\\dbxmlTool\\src\\main\\resources\\CONF\\D\\AionReal58\\AionMap\\XML\\Special01\\direct_portal_special01.json"
												},
												{
													"name":"feather_authorizetable_special01",
													"path":"D:\\workspace\\dbxmlTool\\src\\main\\resources\\CONF\\D\\AionReal58\\AionMap\\XML\\Special01\\feather_authorizetable_special01.json"
												},
												{
													"name":"goodslist_special01",
													"path":"D:\\workspace\\dbxmlTool\\src\\main\\resources\\CONF\\D\\AionReal58\\AionMap\\XML\\Special01\\goodslist_special01.json"
												},
												{
													"name":"hidden_fatigue_special01",
													"path":"D:\\workspace\\dbxmlTool\\src\\main\\resources\\CONF\\D\\AionReal58\\AionMap\\XML\\Special01\\hidden_fatigue_special01.json"
												},
												{
													"name":"infinity_indun_reward_special01",
													"path":"D:\\workspace\\dbxmlTool\\src\\main\\resources\\CONF\\D\\AionReal58\\AionMap\\XML\\Special01\\infinity_indun_reward_special01.json"
												},
												{
													"name":"instance_cooltime2_special01",
													"path":"D:\\workspace\\dbxmlTool\\src\\main\\resources\\CONF\\D\\AionReal58\\AionMap\\XML\\Special01\\instance_cooltime2_special01.json"
												},
												{
													"name":"instance_cooltime_special01",
													"path":"D:\\workspace\\dbxmlTool\\src\\main\\resources\\CONF\\D\\AionReal58\\AionMap\\XML\\Special01\\instance_cooltime_special01.json"
												},
												{
													"name":"instance_scaling_special01",
													"path":"D:\\workspace\\dbxmlTool\\src\\main\\resources\\CONF\\D\\AionReal58\\AionMap\\XML\\Special01\\instance_scaling_special01.json"
												},
												{
													"name":"instant_dungeon_define_special01",
													"path":"D:\\workspace\\dbxmlTool\\src\\main\\resources\\CONF\\D\\AionReal58\\AionMap\\XML\\Special01\\instant_dungeon_define_special01.json"
												},
												{
													"name":"instant_dungeon_idarenapvp_special01",
													"path":"D:\\workspace\\dbxmlTool\\src\\main\\resources\\CONF\\D\\AionReal58\\AionMap\\XML\\Special01\\instant_dungeon_idarenapvp_special01.json"
												},
												{
													"name":"instant_dungeon_tournament_special01",
													"path":"D:\\workspace\\dbxmlTool\\src\\main\\resources\\CONF\\D\\AionReal58\\AionMap\\XML\\Special01\\instant_dungeon_tournament_special01.json"
												},
												{
													"name":"item_authorizetable_special01",
													"path":"D:\\workspace\\dbxmlTool\\src\\main\\resources\\CONF\\D\\AionReal58\\AionMap\\XML\\Special01\\item_authorizetable_special01.json"
												},
												{
													"name":"item_replace_special01",
													"path":"D:\\workspace\\dbxmlTool\\src\\main\\resources\\CONF\\D\\AionReal58\\AionMap\\XML\\Special01\\item_replace_special01.json"
												},
												{
													"name":"item_upgrade_special01",
													"path":"D:\\workspace\\dbxmlTool\\src\\main\\resources\\CONF\\D\\AionReal58\\AionMap\\XML\\Special01\\item_upgrade_special01.json"
												},
												{
													"name":"jumping_pc_special01",
													"path":"D:\\workspace\\dbxmlTool\\src\\main\\resources\\CONF\\D\\AionReal58\\AionMap\\XML\\Special01\\jumping_pc_special01.json"
												},
												{
													"name":"login_event_special01",
													"path":"D:\\workspace\\dbxmlTool\\src\\main\\resources\\CONF\\D\\AionReal58\\AionMap\\XML\\Special01\\login_event_special01.json"
												},
												{
													"name":"matchmaker_special01",
													"path":"D:\\workspace\\dbxmlTool\\src\\main\\resources\\CONF\\D\\AionReal58\\AionMap\\XML\\Special01\\matchmaker_special01.json"
												},
												{
													"name":"monster_scaling_drop_setList_special01",
													"path":"D:\\workspace\\dbxmlTool\\src\\main\\resources\\CONF\\D\\AionReal58\\AionMap\\XML\\Special01\\monster_scaling_drop_setList_special01.json"
												},
												{
													"name":"monster_scaling_drop_special01",
													"path":"D:\\workspace\\dbxmlTool\\src\\main\\resources\\CONF\\D\\AionReal58\\AionMap\\XML\\Special01\\monster_scaling_drop_special01.json"
												},
												{
													"name":"pcexp_table_special01",
													"path":"D:\\workspace\\dbxmlTool\\src\\main\\resources\\CONF\\D\\AionReal58\\AionMap\\XML\\Special01\\pcexp_table_special01.json"
												},
												{
													"name":"pc_death_penalty_special01",
													"path":"D:\\workspace\\dbxmlTool\\src\\main\\resources\\CONF\\D\\AionReal58\\AionMap\\XML\\Special01\\pc_death_penalty_special01.json"
												},
												{
													"name":"pc_level_func_restrict_special01",
													"path":"D:\\workspace\\dbxmlTool\\src\\main\\resources\\CONF\\D\\AionReal58\\AionMap\\XML\\Special01\\pc_level_func_restrict_special01.json"
												},
												{
													"name":"pc_make_up_bonus_special01",
													"path":"D:\\workspace\\dbxmlTool\\src\\main\\resources\\CONF\\D\\AionReal58\\AionMap\\XML\\Special01\\pc_make_up_bonus_special01.json"
												},
												{
													"name":"pc_vital_point_special01",
													"path":"D:\\workspace\\dbxmlTool\\src\\main\\resources\\CONF\\D\\AionReal58\\AionMap\\XML\\Special01\\pc_vital_point_special01.json"
												},
												{
													"name":"pve_adjust_special01",
													"path":"D:\\workspace\\dbxmlTool\\src\\main\\resources\\CONF\\D\\AionReal58\\AionMap\\XML\\Special01\\pve_adjust_special01.json"
												},
												{
													"name":"pvp_rank_special01",
													"path":"D:\\workspace\\dbxmlTool\\src\\main\\resources\\CONF\\D\\AionReal58\\AionMap\\XML\\Special01\\pvp_rank_special01.json"
												},
												{
													"name":"quest_random_rewards_special01",
													"path":"D:\\workspace\\dbxmlTool\\src\\main\\resources\\CONF\\D\\AionReal58\\AionMap\\XML\\Special01\\quest_random_rewards_special01.json"
												},
												{
													"name":"quest_special01",
													"path":"D:\\workspace\\dbxmlTool\\src\\main\\resources\\CONF\\D\\AionReal58\\AionMap\\XML\\Special01\\quest_special01.json"
												},
												{
													"name":"ranking_special01",
													"path":"D:\\workspace\\dbxmlTool\\src\\main\\resources\\CONF\\D\\AionReal58\\AionMap\\XML\\Special01\\ranking_special01.json"
												},
												{
													"name":"serial_killer_special01",
													"path":"D:\\workspace\\dbxmlTool\\src\\main\\resources\\CONF\\D\\AionReal58\\AionMap\\XML\\Special01\\serial_killer_special01.json"
												},
												{
													"name":"toypets_special01",
													"path":"D:\\workspace\\dbxmlTool\\src\\main\\resources\\CONF\\D\\AionReal58\\AionMap\\XML\\Special01\\toypets_special01.json"
												},
												{
													"name":"trade_in_list_special01",
													"path":"D:\\workspace\\dbxmlTool\\src\\main\\resources\\CONF\\D\\AionReal58\\AionMap\\XML\\Special01\\trade_in_list_special01.json"
												},
												{
													"name":"under_control_items_special01",
													"path":"D:\\workspace\\dbxmlTool\\src\\main\\resources\\CONF\\D\\AionReal58\\AionMap\\XML\\Special01\\under_control_items_special01.json"
												},
												{
													"name":"vip_benefit_special01",
													"path":"D:\\workspace\\dbxmlTool\\src\\main\\resources\\CONF\\D\\AionReal58\\AionMap\\XML\\Special01\\vip_benefit_special01.json"
												},
												{
													"name":"vip_grade_exp_special01",
													"path":"D:\\workspace\\dbxmlTool\\src\\main\\resources\\CONF\\D\\AionReal58\\AionMap\\XML\\Special01\\vip_grade_exp_special01.json"
												},
												{
													"name":"world_invasion_special01",
													"path":"D:\\workspace\\dbxmlTool\\src\\main\\resources\\CONF\\D\\AionReal58\\AionMap\\XML\\Special01\\world_invasion_special01.json"
												},
												{
													"name":"world_timeattack_special01",
													"path":"D:\\workspace\\dbxmlTool\\src\\main\\resources\\CONF\\D\\AionReal58\\AionMap\\XML\\Special01\\world_timeattack_special01.json"
												},
												{
													"name":"zonemap_hotspot_special01",
													"path":"D:\\workspace\\dbxmlTool\\src\\main\\resources\\CONF\\D\\AionReal58\\AionMap\\XML\\Special01\\zonemap_hotspot_special01.json"
												}
											],
											"name":"Special01",
											"path":"D:\\workspace\\dbxmlTool\\src\\main\\resources\\CONF\\D\\AionReal58\\AionMap\\XML\\Special01"
										},
										{
											"name":"spvp_time_table",
											"path":"D:\\workspace\\dbxmlTool\\src\\main\\resources\\CONF\\D\\AionReal58\\AionMap\\XML\\spvp_time_table.json"
										},
										{
											"name":"stigma_hiddenskill",
											"path":"D:\\workspace\\dbxmlTool\\src\\main\\resources\\CONF\\D\\AionReal58\\AionMap\\XML\\stigma_hiddenskill.json"
										},
										{
											"name":"toypets",
											"path":"D:\\workspace\\dbxmlTool\\src\\main\\resources\\CONF\\D\\AionReal58\\AionMap\\XML\\toypets.json"
										},
										{
											"name":"toypet_buff",
											"path":"D:\\workspace\\dbxmlTool\\src\\main\\resources\\CONF\\D\\AionReal58\\AionMap\\XML\\toypet_buff.json"
										},
										{
											"name":"toypet_doping",
											"path":"D:\\workspace\\dbxmlTool\\src\\main\\resources\\CONF\\D\\AionReal58\\AionMap\\XML\\toypet_doping.json"
										},
										{
											"name":"toypet_feed",
											"path":"D:\\workspace\\dbxmlTool\\src\\main\\resources\\CONF\\D\\AionReal58\\AionMap\\XML\\toypet_feed.json"
										},
										{
											"name":"toypet_looting",
											"path":"D:\\workspace\\dbxmlTool\\src\\main\\resources\\CONF\\D\\AionReal58\\AionMap\\XML\\toypet_looting.json"
										},
										{
											"name":"toypet_merchant",
											"path":"D:\\workspace\\dbxmlTool\\src\\main\\resources\\CONF\\D\\AionReal58\\AionMap\\XML\\toypet_merchant.json"
										},
										{
											"name":"toypet_warehouse",
											"path":"D:\\workspace\\dbxmlTool\\src\\main\\resources\\CONF\\D\\AionReal58\\AionMap\\XML\\toypet_warehouse.json"
										}
									],
									"name":"XML",
									"path":"D:\\workspace\\dbxmlTool\\src\\main\\resources\\CONF\\D\\AionReal58\\AionMap\\XML"
								},
								{
									"children":[
										{
											"children":[
												{
													"children":[
														{
															"children":[
																{
																	"children":[
																		{
																			"name":"client_assembly_items",
																			"path":"D:\\workspace\\dbxmlTool\\src\\main\\resources\\CONF\\D\\AionReal58\\AionMap\\客户端XML\\data\\China\\items\\items\\client_assembly_items.json"
																		},
																		{
																			"name":"client_combine_recipe",
																			"path":"D:\\workspace\\dbxmlTool\\src\\main\\resources\\CONF\\D\\AionReal58\\AionMap\\客户端XML\\data\\China\\items\\items\\client_combine_recipe.json"
																		},
																		{
																			"name":"client_disassembly_item",
																			"path":"D:\\workspace\\dbxmlTool\\src\\main\\resources\\CONF\\D\\AionReal58\\AionMap\\客户端XML\\data\\China\\items\\items\\client_disassembly_item.json"
																		},
																		{
																			"name":"client_disassembly_item_SetList",
																			"path":"D:\\workspace\\dbxmlTool\\src\\main\\resources\\CONF\\D\\AionReal58\\AionMap\\客户端XML\\data\\China\\items\\items\\client_disassembly_item_SetList.json"
																		},
																		{
																			"name":"client_enchant_cpstone",
																			"path":"D:\\workspace\\dbxmlTool\\src\\main\\resources\\CONF\\D\\AionReal58\\AionMap\\客户端XML\\data\\China\\items\\items\\client_enchant_cpstone.json"
																		},
																		{
																			"name":"client_exchange_equipment",
																			"path":"D:\\workspace\\dbxmlTool\\src\\main\\resources\\CONF\\D\\AionReal58\\AionMap\\客户端XML\\data\\China\\items\\items\\client_exchange_equipment.json"
																		},
																		{
																			"name":"client_items_armor_1",
																			"path":"D:\\workspace\\dbxmlTool\\src\\main\\resources\\CONF\\D\\AionReal58\\AionMap\\客户端XML\\data\\China\\items\\items\\client_items_armor_1.json"
																		},
																		{
																			"name":"client_items_armor_2",
																			"path":"D:\\workspace\\dbxmlTool\\src\\main\\resources\\CONF\\D\\AionReal58\\AionMap\\客户端XML\\data\\China\\items\\items\\client_items_armor_2.json"
																		},
																		{
																			"name":"client_items_etc_1",
																			"path":"D:\\workspace\\dbxmlTool\\src\\main\\resources\\CONF\\D\\AionReal58\\AionMap\\客户端XML\\data\\China\\items\\items\\client_items_etc_1.json"
																		},
																		{
																			"name":"client_items_etc_2",
																			"path":"D:\\workspace\\dbxmlTool\\src\\main\\resources\\CONF\\D\\AionReal58\\AionMap\\客户端XML\\data\\China\\items\\items\\client_items_etc_2.json"
																		},
																		{
																			"name":"client_items_misc",
																			"path":"D:\\workspace\\dbxmlTool\\src\\main\\resources\\CONF\\D\\AionReal58\\AionMap\\客户端XML\\data\\China\\items\\items\\client_items_misc.json"
																		},
																		{
																			"name":"client_item_custom_set",
																			"path":"D:\\workspace\\dbxmlTool\\src\\main\\resources\\CONF\\D\\AionReal58\\AionMap\\客户端XML\\data\\China\\items\\items\\client_item_custom_set.json"
																		},
																		{
																			"name":"client_item_enchanttable",
																			"path":"D:\\workspace\\dbxmlTool\\src\\main\\resources\\CONF\\D\\AionReal58\\AionMap\\客户端XML\\data\\China\\items\\items\\client_item_enchanttable.json"
																		},
																		{
																			"name":"client_item_multi_return",
																			"path":"D:\\workspace\\dbxmlTool\\src\\main\\resources\\CONF\\D\\AionReal58\\AionMap\\客户端XML\\data\\China\\items\\items\\client_item_multi_return.json"
																		},
																		{
																			"name":"client_item_upgrade",
																			"path":"D:\\workspace\\dbxmlTool\\src\\main\\resources\\CONF\\D\\AionReal58\\AionMap\\客户端XML\\data\\China\\items\\items\\client_item_upgrade.json"
																		},
																		{
																			"name":"client_login_event",
																			"path":"D:\\workspace\\dbxmlTool\\src\\main\\resources\\CONF\\D\\AionReal58\\AionMap\\客户端XML\\data\\China\\items\\items\\client_login_event.json"
																		},
																		{
																			"name":"client_npc_goodslist",
																			"path":"D:\\workspace\\dbxmlTool\\src\\main\\resources\\CONF\\D\\AionReal58\\AionMap\\客户端XML\\data\\China\\items\\items\\client_npc_goodslist.json"
																		},
																		{
																			"name":"client_setitem",
																			"path":"D:\\workspace\\dbxmlTool\\src\\main\\resources\\CONF\\D\\AionReal58\\AionMap\\客户端XML\\data\\China\\items\\items\\client_setitem.json"
																		}
																	],
																	"name":"items",
																	"path":"D:\\workspace\\dbxmlTool\\src\\main\\resources\\CONF\\D\\AionReal58\\AionMap\\客户端XML\\data\\China\\items\\items"
																}
															],
															"name":"items",
															"path":"D:\\workspace\\dbxmlTool\\src\\main\\resources\\CONF\\D\\AionReal58\\AionMap\\客户端XML\\data\\China\\items"
														},
														{
															"children":[
																{
																	"children":[
																		{
																			"name":"client_npcs_abyss_monster",
																			"path":"D:\\workspace\\dbxmlTool\\src\\main\\resources\\CONF\\D\\AionReal58\\AionMap\\客户端XML\\data\\China\\Npcs\\npcs\\client_npcs_abyss_monster.json"
																		},
																		{
																			"name":"client_npcs_npc",
																			"path":"D:\\workspace\\dbxmlTool\\src\\main\\resources\\CONF\\D\\AionReal58\\AionMap\\客户端XML\\data\\China\\Npcs\\npcs\\client_npcs_npc.json"
																		},
																		{
																			"name":"client_npc_goodslist",
																			"path":"D:\\workspace\\dbxmlTool\\src\\main\\resources\\CONF\\D\\AionReal58\\AionMap\\客户端XML\\data\\China\\Npcs\\npcs\\client_npc_goodslist.json"
																		},
																		{
																			"name":"client_npc_purchase_list",
																			"path":"D:\\workspace\\dbxmlTool\\src\\main\\resources\\CONF\\D\\AionReal58\\AionMap\\客户端XML\\data\\China\\Npcs\\npcs\\client_npc_purchase_list.json"
																		},
																		{
																			"name":"client_npc_trade_in_list",
																			"path":"D:\\workspace\\dbxmlTool\\src\\main\\resources\\CONF\\D\\AionReal58\\AionMap\\客户端XML\\data\\China\\Npcs\\npcs\\client_npc_trade_in_list.json"
																		}
																	],
																	"name":"npcs",
																	"path":"D:\\workspace\\dbxmlTool\\src\\main\\resources\\CONF\\D\\AionReal58\\AionMap\\客户端XML\\data\\China\\Npcs\\npcs"
																}
															],
															"name":"Npcs",
															"path":"D:\\workspace\\dbxmlTool\\src\\main\\resources\\CONF\\D\\AionReal58\\AionMap\\客户端XML\\data\\China\\Npcs"
														},
														{
															"children":[
																{
																	"children":[
																		{
																			"name":"combine_task",
																			"path":"D:\\workspace\\dbxmlTool\\src\\main\\resources\\CONF\\D\\AionReal58\\AionMap\\客户端XML\\data\\China\\Quest\\quest\\combine_task.json"
																		},
																		{
																			"name":"quest",
																			"path":"D:\\workspace\\dbxmlTool\\src\\main\\resources\\CONF\\D\\AionReal58\\AionMap\\客户端XML\\data\\China\\Quest\\quest\\quest.json"
																		}
																	],
																	"name":"quest",
																	"path":"D:\\workspace\\dbxmlTool\\src\\main\\resources\\CONF\\D\\AionReal58\\AionMap\\客户端XML\\data\\China\\Quest\\quest"
																}
															],
															"name":"Quest",
															"path":"D:\\workspace\\dbxmlTool\\src\\main\\resources\\CONF\\D\\AionReal58\\AionMap\\客户端XML\\data\\China\\Quest"
														},
														{
															"children":[
																{
																	"children":[
																		{
																			"name":"client_absolute_stat_to_pc",
																			"path":"D:\\workspace\\dbxmlTool\\src\\main\\resources\\CONF\\D\\AionReal58\\AionMap\\客户端XML\\data\\China\\skills\\skills\\client_absolute_stat_to_pc.json"
																		},
																		{
																			"name":"client_abyss_leader_skill",
																			"path":"D:\\workspace\\dbxmlTool\\src\\main\\resources\\CONF\\D\\AionReal58\\AionMap\\客户端XML\\data\\China\\skills\\skills\\client_abyss_leader_skill.json"
																		},
																		{
																			"name":"client_pc_skill_skin",
																			"path":"D:\\workspace\\dbxmlTool\\src\\main\\resources\\CONF\\D\\AionReal58\\AionMap\\客户端XML\\data\\China\\skills\\skills\\client_pc_skill_skin.json"
																		},
																		{
																			"name":"client_polymorph_temp_skill",
																			"path":"D:\\workspace\\dbxmlTool\\src\\main\\resources\\CONF\\D\\AionReal58\\AionMap\\客户端XML\\data\\China\\skills\\skills\\client_polymorph_temp_skill.json"
																		},
																		{
																			"name":"client_skills",
																			"path":"D:\\workspace\\dbxmlTool\\src\\main\\resources\\CONF\\D\\AionReal58\\AionMap\\客户端XML\\data\\China\\skills\\skills\\client_skills.json"
																		},
																		{
																			"name":"client_skill_charge",
																			"path":"D:\\workspace\\dbxmlTool\\src\\main\\resources\\CONF\\D\\AionReal58\\AionMap\\客户端XML\\data\\China\\skills\\skills\\client_skill_charge.json"
																		},
																		{
																			"name":"client_skill_learns",
																			"path":"D:\\workspace\\dbxmlTool\\src\\main\\resources\\CONF\\D\\AionReal58\\AionMap\\客户端XML\\data\\China\\skills\\skills\\client_skill_learns.json"
																		},
																		{
																			"name":"client_skill_prohibit",
																			"path":"D:\\workspace\\dbxmlTool\\src\\main\\resources\\CONF\\D\\AionReal58\\AionMap\\客户端XML\\data\\China\\skills\\skills\\client_skill_prohibit.json"
																		},
																		{
																			"name":"client_ultra_skills",
																			"path":"D:\\workspace\\dbxmlTool\\src\\main\\resources\\CONF\\D\\AionReal58\\AionMap\\客户端XML\\data\\China\\skills\\skills\\client_ultra_skills.json"
																		},
																		{
																			"name":"conditional_bonuses",
																			"path":"D:\\workspace\\dbxmlTool\\src\\main\\resources\\CONF\\D\\AionReal58\\AionMap\\客户端XML\\data\\China\\skills\\skills\\conditional_bonuses.json"
																		},
																		{
																			"name":"skill_shortcut_replace",
																			"path":"D:\\workspace\\dbxmlTool\\src\\main\\resources\\CONF\\D\\AionReal58\\AionMap\\客户端XML\\data\\China\\skills\\skills\\skill_shortcut_replace.json"
																		}
																	],
																	"name":"skills",
																	"path":"D:\\workspace\\dbxmlTool\\src\\main\\resources\\CONF\\D\\AionReal58\\AionMap\\客户端XML\\data\\China\\skills\\skills"
																}
															],
															"name":"skills",
															"path":"D:\\workspace\\dbxmlTool\\src\\main\\resources\\CONF\\D\\AionReal58\\AionMap\\客户端XML\\data\\China\\skills"
														}
													],
													"name":"China",
													"path":"D:\\workspace\\dbxmlTool\\src\\main\\resources\\CONF\\D\\AionReal58\\AionMap\\客户端XML\\data\\China"
												},
												{
													"name":"guild_emblem",
													"path":"D:\\workspace\\dbxmlTool\\src\\main\\resources\\CONF\\D\\AionReal58\\AionMap\\客户端XML\\data\\guild_emblem.json"
												},
												{
													"children":[
														{
															"name":"combine_task",
															"path":"D:\\workspace\\dbxmlTool\\src\\main\\resources\\CONF\\D\\AionReal58\\AionMap\\客户端XML\\data\\Quest\\combine_task.json"
														}
													],
													"name":"Quest",
													"path":"D:\\workspace\\dbxmlTool\\src\\main\\resources\\CONF\\D\\AionReal58\\AionMap\\客户端XML\\data\\Quest"
												}
											],
											"name":"data",
											"path":"D:\\workspace\\dbxmlTool\\src\\main\\resources\\CONF\\D\\AionReal58\\AionMap\\客户端XML\\data"
										}
									],
									"name":"客户端XML",
									"path":"D:\\workspace\\dbxmlTool\\src\\main\\resources\\CONF\\D\\AionReal58\\AionMap\\客户端XML"
								}
							],
							"name":"AionMap",
							"path":"D:\\workspace\\dbxmlTool\\src\\main\\resources\\CONF\\D\\AionReal58\\AionMap"
						}
					],
					"name":"AionReal58",
					"path":"D:\\workspace\\dbxmlTool\\src\\main\\resources\\CONF\\D\\AionReal58"
				}
			],
			"name":"D",
			"path":"D:\\workspace\\dbxmlTool\\src\\main\\resources\\CONF\\D"
		}
	],
	"name":"CONF",
	"path":"D:\\workspace\\dbxmlTool\\src\\main\\resources\\CONF"
}