{
	"file_path":"D:\\AionReal58\\AionMap\\客户端XML\\data\\China\\items\\items\\client_item_multi_return.xml",
	"xml_root_tag":"client_item_multi_returns",
	"list":[
		{
			"addDataNode":"return_loc_list",
			"associatedFiled":"id",
			"xml_tag":"data",
			"db_column":"data",
			"table_name":"client_item_multi_return__return_loc_list__data",
			"sql":"select * from client_item_multi_return__return_loc_list__data where id = '#associated_filed' order by CAST(id AS UNSIGNED) ASC"
		}
	],
	"xml_item_tag":"client_item_multi_return",
	"table_name":"client_item_multi_return",
	"sql":"select * from client_item_multi_return order by CAST(id AS UNSIGNED) ASC"
}