{
	"file_path":"D:\\AionReal58\\AionMap\\XML\\toypets.xml",
	"xml_root_tag":"toypets",
	"list":[
		{
			"addDataNode":"ui_colors",
			"associatedFiled":"id",
			"xml_tag":"data",
			"db_column":"data",
			"table_name":"toypets__ui_colors__data",
			"sql":"select * from toypets__ui_colors__data where id = '#associated_filed' order by CAST(id AS UNSIGNED) ASC"
		},
		{
			"addDataNode":"",
			"associatedFiled":"id",
			"xml_tag":"bound_radius",
			"db_column":"bound_radius",
			"table_name":"toypets__bound_radius",
			"sql":"select * from toypets__bound_radius where id = '#associated_filed' order by CAST(id AS UNSIGNED) ASC"
		}
	],
	"xml_item_tag":"toypet",
	"table_name":"toypets",
	"sql":"select * from toypets order by CAST(id AS UNSIGNED) ASC"
}